<?xml version="1.0" encoding="UTF-8" ?>
<suite name="test">
    <test name="testall">
        <classes>

            <class name="come.course.testng.groups.groupsonclass1"/>
            <class name="come.course.testng.groups.groupsonclass2"/>
            <class name="come.course.testng.groups.groupsonclass3"/>
        </classes>
    </test>


    <test name="testclass1">
        <groups>
            <run>
                <include name="stu"/>
            </run>
        </groups>
        <classes>

            <class name="come.course.testng.groups.groupsonclass1"/>
            <class name="come.course.testng.groups.groupsonclass2"/>
            <class name="come.course.testng.groups.groupsonclass3"/>
        </classes>
    </test>
</suite>